odoo/addons/l10n_nl_postcodeapi/README.rst
odoo/addons/l10n_nl_postcodeapi/__init__.py
odoo/addons/l10n_nl_postcodeapi/__manifest__.py
odoo/addons/l10n_nl_postcodeapi/data/ir_config_parameter.xml
odoo/addons/l10n_nl_postcodeapi/i18n/l10n_nl_postcodeapi.pot
odoo/addons/l10n_nl_postcodeapi/i18n/nl.po
odoo/addons/l10n_nl_postcodeapi/models/__init__.py
odoo/addons/l10n_nl_postcodeapi/models/ir_config_parameter.py
odoo/addons/l10n_nl_postcodeapi/models/res_partner.py
odoo/addons/l10n_nl_postcodeapi/readme/CONFIGURE.rst
odoo/addons/l10n_nl_postcodeapi/readme/CONTRIBUTORS.rst
odoo/addons/l10n_nl_postcodeapi/readme/DESCRIPTION.rst
odoo/addons/l10n_nl_postcodeapi/readme/HISTORY.rst
odoo/addons/l10n_nl_postcodeapi/readme/INSTALL.rst
odoo/addons/l10n_nl_postcodeapi/static/description/icon.png
odoo/addons/l10n_nl_postcodeapi/static/description/index.html
odoo/addons/l10n_nl_postcodeapi/tests/__init__.py
odoo/addons/l10n_nl_postcodeapi/tests/test_l10n_nl_postcodeapi.py
odoo12_addon_l10n_nl_postcodeapi-12.0.2.0.0.99.dev5.dist-info/METADATA
odoo12_addon_l10n_nl_postcodeapi-12.0.2.0.0.99.dev5.dist-info/WHEEL
odoo12_addon_l10n_nl_postcodeapi-12.0.2.0.0.99.dev5.dist-info/top_level.txt
odoo12_addon_l10n_nl_postcodeapi-12.0.2.0.0.99.dev5.dist-info/RECORD
