Metadata-Version: 2.1
Name: odoo12-addon-l10n-nl-postcodeapi
Version: 12.0.2.0.0.99.dev5
Summary: Autocomplete Dutch addresses using PostcodeApi.nu
Home-page: https://github.com/OCA/l10n-netherlands
Author: Therp BV,Odoo Community Association (OCA)
Author-email: support@odoo-community.org
License: AGPL-3
Platform: UNKNOWN
Classifier: Programming Language :: Python
Classifier: Framework :: Odoo
Classifier: Framework :: Odoo :: 12.0
Classifier: License :: OSI Approved :: GNU Affero General Public License v3
Requires-Python: >=3.5
Requires-Dist: odoo12-addon-l10n-nl-country-states
Requires-Dist: odoo <12.1dev,>=12.0a
Requires-Dist: pyPostcode
